yanniszark_common/__init__.py
yanniszark_common/blkutils.py
yanniszark_common/cmdutils.py
yanniszark_common/fileutils.py
yanniszark_common/gitutils.py
yanniszark_common/installutils.py
yanniszark_common/netutils.py
yanniszark_common-0.1.140.dist-info/METADATA
yanniszark_common-0.1.140.dist-info/WHEEL
yanniszark_common-0.1.140.dist-info/RECORD
