Metadata-Version: 2.3
Name: yanniszark_common
Version: 0.1.140
Summary: Idiomatic, reusable code for a bunch of use-cases.
Author: Yannis Zarkadas
Author-email: yanniszark@gmail.com
Requires-Python: >=3.8,<4.0
Classifier: Programming Language :: Python :: 3
Classifier: Programming Language :: Python :: 3.8
Classifier: Programming Language :: Python :: 3.9
Classifier: Programming Language :: Python :: 3.10
Classifier: Programming Language :: Python :: 3.11
Classifier: Programming Language :: Python :: 3.12
Classifier: Programming Language :: Python :: 3.13
Requires-Dist: GitPython (>=3.1.27,<4.0.0)
Requires-Dist: requests (>=2.28.1,<3.0.0)
